_examples/__init__.py
examples/__init__.py
objcache/__init__.py
objcache/logic/__init__.py
objcache/logic/seed.py
objcache/logic/subpath.py
objcache/models/__init__.py
objcache/models/object_cache.py
tests/__init__.py
tests/test_object_cache.py
tests/utils.py
objcache-0.1.1.dist-info/LICENSE.md
objcache-0.1.1.dist-info/METADATA
objcache-0.1.1.dist-info/WHEEL
objcache-0.1.1.dist-info/entry_points.txt
objcache-0.1.1.dist-info/top_level.txt
objcache-0.1.1.dist-info/RECORD
