Metadata-Version: 2.1
Name: objcache
Version: 0.1.1
Summary: Simple Redis-like interface to storing arbirary Python objects. A high-level wrapper around ZoDB.
Home-page: https://github.com/nickderobertis/obj-cache
Author: Nick DeRobertis
Author-email: whoopnip@gmail.com
License: MIT
Project-URL: Code, https://github.com/nickderobertis/obj-cache
Project-URL: Documentation, https://nickderobertis.github.io/obj-cache
Platform: UNKNOWN
Classifier: Development Status :: 3 - Alpha
Classifier: Intended Audience :: Developers
Classifier: Programming Language :: Python :: 3.6
Classifier: Programming Language :: Python :: 3.7
Requires-Dist: ZoDB
